netlink/crypt/__init__.py
netlink/crypt/cli.py
netlink/crypt/crypt.py
netlink/crypt/linux.py
netlink/crypt/win32.py
netlink_crypt-0.0.1.dist-info/entry_points.txt
netlink_crypt-0.0.1.dist-info/WHEEL
netlink_crypt-0.0.1.dist-info/METADATA
netlink_crypt-0.0.1.dist-info/RECORD
