Metadata-Version: 2.1
Name: netlink-crypt
Version: 0.0.1
Summary: Password Storage for Automation
Home-page: https://gitlab.com/netlink_python/netlink-crypt
License: MIT
Keywords: password automation
Author: Bernhard Radermacher
Author-email: bernhard.radermacher@netlink-consulting.com
Requires-Python: >=3.7,<3.11
Classifier: License :: OSI Approved :: MIT License
Classifier: Programming Language :: Python :: 3
Classifier: Programming Language :: Python :: 3.10
Classifier: Programming Language :: Python :: 3.7
Classifier: Programming Language :: Python :: 3.8
Classifier: Programming Language :: Python :: 3.9
Classifier: Topic :: Software Development
Requires-Dist: click (>=8.1.3,<9.0.0)
Requires-Dist: pycryptodomex (>=3.14.1,<4.0.0)
Requires-Dist: pywin32 (>=304,<305); sys_platform == "win32"
Project-URL: Repository, https://gitlab.com/netlink_python/netlink-crypt
